ankisiyuan/__init__.py
ankisiyuan/__main__.py
ankisiyuan/cli.py
ankisiyuan/config.py
ankisiyuan/config.toml
ankisiyuan/config_parser.py
ankisiyuan/notetypes/SCloze.py
ankisiyuan/notetypes/SListCloze.py
ankisiyuan/notetypes/SMQA.py
ankisiyuan/notetypes/SQA.py
ankisiyuan/notetypes/STableCloze.py
ankisiyuan/notetypes/SWatch.py
ankisiyuan/notetypes/__init__.py
ankisiyuan/parsers/__init__.py
ankisiyuan/parsers/siyuan.py
ankisiyuan-0.1.1.dist-info/LICENSE
ankisiyuan-0.1.1.dist-info/WHEEL
ankisiyuan-0.1.1.dist-info/METADATA
ankisiyuan-0.1.1.dist-info/RECORD
